[[{"originalTime":"2020-07-07T03:51:25Z","parsedTime":"2020-07-07 03:51:25","unixTime":1594050685000,"elapsedTime":"00:09:40","incrementalDistance":2,"cumulativeDistance":461,"wSpeed":null,"pSpeed":3.6,"isWave":false},{"originalTime":"2020-07-07T03:51:27Z","parsedTime":"2020-07-07 03:51:27","unixTime":1594050687000,"elapsedTime":"00:09:42","incrementalDistance":2,"cumulativeDistance":463,"wSpeed":9.6,"pSpeed":null,"isWave":true},{"originalTime":"2020-07-07T03:51:28Z","parsedTime":"2020-07-07 03:51:28","unixTime":1594050688000,"elapsedTime":"00:09:43","incrementalDistance":5,"cumulativeDistance":468,"wSpeed":11.4,"pSpeed":null,"isWave":true},{"originalTime":"2020-07-07T03:51:29Z","parsedTime":"2020-07-07 03:51:29","unixTime":1594050689000,"elapsedTime":"00:09:44","incrementalDistance":5,"cumulativeDistance":473,"wSpeed":10,"pSpeed":null,"isWave":true}],[{"originalTime":"2020-07-07T03:55:43Z","parsedTime":"2020-07-07 03:55:43","unixTime":1594050943000,"elapsedTime":"00:13:58","incrementalDistance":6,"cumulativeDistance":668,"wSpeed":null,"pSpeed":6.840000000000001,"isWave":false},{"originalTime":"2020-07-07T03:55:47Z","parsedTime":"2020-07-07 03:55:47","unixTime":1594050947000,"elapsedTime":"00:14:02","incrementalDistance":6,"cumulativeDistance":674,"wSpeed":9.600000000000001,"pSpeed":null,"isWave":true},{"originalTime":"2020-07-07T03:55:49Z","parsedTime":"2020-07-07 03:55:49","unixTime":1594050949000,"elapsedTime":"00:14:04","incrementalDistance":7,"cumulativeDistance":681,"wSpeed":14.314285714285715,"pSpeed":null,"isWave":true},{"originalTime":"2020-07-07T03:55:51Z","parsedTime":"2020-07-07 03:55:51","unixTime":1594050951000,"elapsedTime":"00:14:06","incrementalDistance":38,"cumulativeDistance":719,"wSpeed":18.714285714285715,"pSpeed":null,"isWave":true},{"originalTime":"2020-07-07T03:55:58Z","parsedTime":"2020-07-07 03:55:58","unixTime":1594050958000,"elapsedTime":"00:14:13","incrementalDistance":20,"cumulativeDistance":739,"wSpeed":15.247619047619049,"pSpeed":null,"isWave":true},{"originalTime":"2020-07-07T03:56:01Z","parsedTime":"2020-07-07 03:56:01","unixTime":1594050961000,"elapsedTime":"00:14:16","incrementalDistance":11,"cumulativeDistance":750,"wSpeed":10.533333333333333,"pSpeed":null,"isWave":true}],[{"originalTime":"2020-07-07T03:57:32Z","parsedTime":"2020-07-07 03:57:32","unixTime":1594051052000,"elapsedTime":"00:15:47","incrementalDistance":10,"cumulativeDistance":861,"wSpeed":null,"pSpeed":3.3000000000000003,"isWave":false},{"originalTime":"2020-07-07T03:57:56Z","parsedTime":"2020-07-07 03:57:56","unixTime":1594051076000,"elapsedTime":"00:16:11","incrementalDistance":10,"cumulativeDistance":871,"wSpeed":12.5,"pSpeed":null,"isWave":true},{"originalTime":"2020-07-07T03:58:02Z","parsedTime":"2020-07-07 03:58:02","unixTime":1594051082000,"elapsedTime":"00:16:17","incrementalDistance":10,"cumulativeDistance":881,"wSpeed":15.200000000000001,"pSpeed":null,"isWave":true},{"originalTime":"2020-07-07T03:58:03Z","parsedTime":"2020-07-07 03:58:03","unixTime":1594051083000,"elapsedTime":"00:16:18","incrementalDistance":24,"cumulativeDistance":905,"wSpeed":16,"pSpeed":null,"isWave":true}],[{"originalTime":"2020-07-07T04:03:27Z","parsedTime":"2020-07-07 04:03:27","unixTime":1594051407000,"elapsedTime":"00:21:42","incrementalDistance":0,"cumulativeDistance":1181,"wSpeed":null,"pSpeed":0,"isWave":false},{"originalTime":"2020-07-07T04:03:29Z","parsedTime":"2020-07-07 04:03:29","unixTime":1594051409000,"elapsedTime":"00:21:44","incrementalDistance":0,"cumulativeDistance":1181,"wSpeed":10,"pSpeed":null,"isWave":true},{"originalTime":"2020-07-07T04:03:34Z","parsedTime":"2020-07-07 04:03:34","unixTime":1594051414000,"elapsedTime":"00:21:49","incrementalDistance":21,"cumulativeDistance":1202,"wSpeed":11.200000000000001,"pSpeed":null,"isWave":true},{"originalTime":"2020-07-07T04:03:36Z","parsedTime":"2020-07-07 04:03:36","unixTime":1594051416000,"elapsedTime":"00:21:51","incrementalDistance":1,"cumulativeDistance":1203,"wSpeed":11.270588235294118,"pSpeed":null,"isWave":true}],[{"originalTime":"2020-07-07T04:05:58Z","parsedTime":"2020-07-07 04:05:58","unixTime":1594051558000,"elapsedTime":"00:24:13","incrementalDistance":3,"cumulativeDistance":1343,"wSpeed":null,"pSpeed":6,"isWave":false},{"originalTime":"2020-07-07T04:05:59Z","parsedTime":"2020-07-07 04:05:59","unixTime":1594051559000,"elapsedTime":"00:24:14","incrementalDistance":1,"cumulativeDistance":1344,"wSpeed":12,"pSpeed":null,"isWave":true},{"originalTime":"2020-07-07T04:06:00Z","parsedTime":"2020-07-07 04:06:00","unixTime":1594051560000,"elapsedTime":"00:24:15","incrementalDistance":6,"cumulativeDistance":1350,"wSpeed":9.600000000000001,"pSpeed":null,"isWave":true},{"originalTime":"2020-07-07T04:06:01Z","parsedTime":"2020-07-07 04:06:01","unixTime":1594051561000,"elapsedTime":"00:24:16","incrementalDistance":1,"cumulativeDistance":1351,"wSpeed":9.9,"pSpeed":null,"isWave":true}],[{"originalTime":"2020-07-07T04:07:58Z","parsedTime":"2020-07-07 04:07:58","unixTime":1594051678000,"elapsedTime":"00:26:13","incrementalDistance":5,"cumulativeDistance":1465,"wSpeed":null,"pSpeed":5.533333333333334,"isWave":false},{"originalTime":"2020-07-07T04:08:00Z","parsedTime":"2020-07-07 04:08:00","unixTime":1594051680000,"elapsedTime":"00:26:15","incrementalDistance":1,"cumulativeDistance":1466,"wSpeed":8.4,"pSpeed":null,"isWave":true},{"originalTime":"2020-07-07T04:08:01Z","parsedTime":"2020-07-07 04:08:01","unixTime":1594051681000,"elapsedTime":"00:26:16","incrementalDistance":7,"cumulativeDistance":1473,"wSpeed":11.799999999999999,"pSpeed":null,"isWave":true},{"originalTime":"2020-07-07T04:08:03Z","parsedTime":"2020-07-07 04:08:03","unixTime":1594051683000,"elapsedTime":"00:26:18","incrementalDistance":16,"cumulativeDistance":1489,"wSpeed":11.159999999999998,"pSpeed":null,"isWave":true},{"originalTime":"2020-07-07T04:08:06Z","parsedTime":"2020-07-07 04:08:06","unixTime":1594051686000,"elapsedTime":"00:26:21","incrementalDistance":7,"cumulativeDistance":1496,"wSpeed":8.16,"pSpeed":null,"isWave":true}],[{"originalTime":"2020-07-07T04:12:08Z","parsedTime":"2020-07-07 04:12:08","unixTime":1594051928000,"elapsedTime":"00:30:23","incrementalDistance":0,"cumulativeDistance":1652,"wSpeed":null,"pSpeed":4.3999999999999995,"isWave":false},{"originalTime":"2020-07-07T04:12:10Z","parsedTime":"2020-07-07 04:12:10","unixTime":1594051930000,"elapsedTime":"00:30:25","incrementalDistance":22,"cumulativeDistance":1674,"wSpeed":9.799999999999999,"pSpeed":null,"isWave":true},{"originalTime":"2020-07-07T04:12:16Z","parsedTime":"2020-07-07 04:12:16","unixTime":1594051936000,"elapsedTime":"00:30:31","incrementalDistance":18,"cumulativeDistance":1692,"wSpeed":11.149999999999999,"pSpeed":null,"isWave":true},{"originalTime":"2020-07-07T04:12:20Z","parsedTime":"2020-07-07 04:12:20","unixTime":1594051940000,"elapsedTime":"00:30:35","incrementalDistance":9,"cumulativeDistance":1701,"wSpeed":9.6,"pSpeed":null,"isWave":true}],[{"originalTime":"2020-07-07T04:19:37Z","parsedTime":"2020-07-07 04:19:37","unixTime":1594052377000,"elapsedTime":"00:37:52","incrementalDistance":1,"cumulativeDistance":2027,"wSpeed":null,"pSpeed":2.1999999999999997,"isWave":false},{"originalTime":"2020-07-07T04:19:39Z","parsedTime":"2020-07-07 04:19:39","unixTime":1594052379000,"elapsedTime":"00:37:54","incrementalDistance":0,"cumulativeDistance":2027,"wSpeed":10.6,"pSpeed":null,"isWave":true},{"originalTime":"2020-07-07T04:19:49Z","parsedTime":"2020-07-07 04:19:49","unixTime":1594052389000,"elapsedTime":"00:38:04","incrementalDistance":34,"cumulativeDistance":2061,"wSpeed":11.68,"pSpeed":null,"isWave":true},{"originalTime":"2020-07-07T04:19:52Z","parsedTime":"2020-07-07 04:19:52","unixTime":1594052392000,"elapsedTime":"00:38:07","incrementalDistance":7,"cumulativeDistance":2068,"wSpeed":13.68,"pSpeed":null,"isWave":true},{"originalTime":"2020-07-07T04:19:57Z","parsedTime":"2020-07-07 04:19:57","unixTime":1594052397000,"elapsedTime":"00:38:12","incrementalDistance":10,"cumulativeDistance":2078,"wSpeed":null,"pSpeed":5.6000000000000005,"isWave":false},{"originalTime":"2020-07-07T04:20:03Z","parsedTime":"2020-07-07 04:20:03","unixTime":1594052403000,"elapsedTime":"00:38:18","incrementalDistance":8,"cumulativeDistance":2086,"wSpeed":9.32,"pSpeed":null,"isWave":true},{"originalTime":"2020-07-07T04:20:08Z","parsedTime":"2020-07-07 04:20:08","unixTime":1594052408000,"elapsedTime":"00:38:23","incrementalDistance":9,"cumulativeDistance":2095,"wSpeed":8.520000000000001,"pSpeed":null,"isWave":true}],[{"originalTime":"2020-07-07T04:20:46Z","parsedTime":"2020-07-07 04:20:46","unixTime":1594052446000,"elapsedTime":"00:39:01","incrementalDistance":14,"cumulativeDistance":2117,"wSpeed":null,"pSpeed":6.246153846153845,"isWave":false},{"originalTime":"2020-07-07T04:20:59Z","parsedTime":"2020-07-07 04:20:59","unixTime":1594052459000,"elapsedTime":"00:39:14","incrementalDistance":11,"cumulativeDistance":2128,"wSpeed":11.452307692307693,"pSpeed":null,"isWave":true},{"originalTime":"2020-07-07T04:21:02Z","parsedTime":"2020-07-07 04:21:02","unixTime":1594052462000,"elapsedTime":"00:39:17","incrementalDistance":24,"cumulativeDistance":2152,"wSpeed":16.96,"pSpeed":null,"isWave":true},{"originalTime":"2020-07-07T04:21:07Z","parsedTime":"2020-07-07 04:21:07","unixTime":1594052467000,"elapsedTime":"00:39:22","incrementalDistance":17,"cumulativeDistance":2169,"wSpeed":19.76,"pSpeed":null,"isWave":true},{"originalTime":"2020-07-07T04:21:10Z","parsedTime":"2020-07-07 04:21:10","unixTime":1594052470000,"elapsedTime":"00:39:25","incrementalDistance":12,"cumulativeDistance":2181,"wSpeed":19.400000000000002,"pSpeed":null,"isWave":true},{"originalTime":"2020-07-07T04:21:12Z","parsedTime":"2020-07-07 04:21:12","unixTime":1594052472000,"elapsedTime":"00:39:27","incrementalDistance":9,"cumulativeDistance":2190,"wSpeed":17.4,"pSpeed":null,"isWave":true},{"originalTime":"2020-07-07T04:21:14Z","parsedTime":"2020-07-07 04:21:14","unixTime":1594052474000,"elapsedTime":"00:39:29","incrementalDistance":24,"cumulativeDistance":2214,"wSpeed":13.200000000000001,"pSpeed":null,"isWave":true},{"originalTime":"2020-07-07T04:21:20Z","parsedTime":"2020-07-07 04:21:20","unixTime":1594052480000,"elapsedTime":"00:39:35","incrementalDistance":10,"cumulativeDistance":2224,"wSpeed":10.2,"pSpeed":null,"isWave":true}],[{"originalTime":"2020-07-07T04:24:59Z","parsedTime":"2020-07-07 04:24:59","unixTime":1594052699000,"elapsedTime":"00:43:14","incrementalDistance":0,"cumulativeDistance":2414,"wSpeed":null,"pSpeed":0,"isWave":false},{"originalTime":"2020-07-07T04:25:01Z","parsedTime":"2020-07-07 04:25:01","unixTime":1594052701000,"elapsedTime":"00:43:16","incrementalDistance":0,"cumulativeDistance":2414,"wSpeed":10,"pSpeed":null,"isWave":true},{"originalTime":"2020-07-07T04:25:03Z","parsedTime":"2020-07-07 04:25:03","unixTime":1594052703000,"elapsedTime":"00:43:18","incrementalDistance":24,"cumulativeDistance":2438,"wSpeed":13.9,"pSpeed":null,"isWave":true},{"originalTime":"2020-07-07T04:25:05Z","parsedTime":"2020-07-07 04:25:05","unixTime":1594052705000,"elapsedTime":"00:43:20","incrementalDistance":13,"cumulativeDistance":2451,"wSpeed":16.6,"pSpeed":null,"isWave":true}],[{"originalTime":"2020-07-07T04:27:23Z","parsedTime":"2020-07-07 04:27:23","unixTime":1594052843000,"elapsedTime":"00:45:38","incrementalDistance":0,"cumulativeDistance":2585,"wSpeed":null,"pSpeed":7.6000000000000005,"isWave":false},{"originalTime":"2020-07-07T04:27:28Z","parsedTime":"2020-07-07 04:27:28","unixTime":1594052848000,"elapsedTime":"00:45:43","incrementalDistance":10,"cumulativeDistance":2595,"wSpeed":8.700000000000001,"pSpeed":null,"isWave":true},{"originalTime":"2020-07-07T04:27:30Z","parsedTime":"2020-07-07 04:27:30","unixTime":1594052850000,"elapsedTime":"00:45:45","incrementalDistance":9,"cumulativeDistance":2604,"wSpeed":10.166666666666666,"pSpeed":null,"isWave":true},{"originalTime":"2020-07-07T04:27:34Z","parsedTime":"2020-07-07 04:27:34","unixTime":1594052854000,"elapsedTime":"00:45:49","incrementalDistance":11,"cumulativeDistance":2615,"wSpeed":null,"pSpeed":4.166666666666667,"isWave":false},{"originalTime":"2020-07-07T04:27:43Z","parsedTime":"2020-07-07 04:27:43","unixTime":1594052863000,"elapsedTime":"00:45:58","incrementalDistance":0,"cumulativeDistance":2615,"wSpeed":9.266666666666667,"pSpeed":null,"isWave":true},{"originalTime":"2020-07-07T04:27:47Z","parsedTime":"2020-07-07 04:27:47","unixTime":1594052867000,"elapsedTime":"00:46:02","incrementalDistance":13,"cumulativeDistance":2628,"wSpeed":12.600000000000001,"pSpeed":null,"isWave":true},{"originalTime":"2020-07-07T04:27:49Z","parsedTime":"2020-07-07 04:27:49","unixTime":1594052869000,"elapsedTime":"00:46:04","incrementalDistance":8,"cumulativeDistance":2636,"wSpeed":17.400000000000002,"pSpeed":null,"isWave":true},{"originalTime":"2020-07-07T04:27:51Z","parsedTime":"2020-07-07 04:27:51","unixTime":1594052871000,"elapsedTime":"00:46:06","incrementalDistance":4,"cumulativeDistance":2640,"wSpeed":12.72,"pSpeed":null,"isWave":true},{"originalTime":"2020-07-07T04:27:52Z","parsedTime":"2020-07-07 04:27:52","unixTime":1594052872000,"elapsedTime":"00:46:07","incrementalDistance":13,"cumulativeDistance":2653,"wSpeed":8.92,"pSpeed":null,"isWave":true}],[{"originalTime":"2020-07-07T04:31:40Z","parsedTime":"2020-07-07 04:31:40","unixTime":1594053100000,"elapsedTime":"00:49:55","incrementalDistance":0,"cumulativeDistance":2757,"wSpeed":null,"pSpeed":3.8000000000000003,"isWave":false},{"originalTime":"2020-07-07T04:31:41Z","parsedTime":"2020-07-07 04:31:41","unixTime":1594053101000,"elapsedTime":"00:49:56","incrementalDistance":19,"cumulativeDistance":2776,"wSpeed":11.600000000000001,"pSpeed":null,"isWave":true},{"originalTime":"2020-07-07T04:31:47Z","parsedTime":"2020-07-07 04:31:47","unixTime":1594053107000,"elapsedTime":"00:50:02","incrementalDistance":13,"cumulativeDistance":2789,"wSpeed":20,"pSpeed":null,"isWave":true},{"originalTime":"2020-07-07T04:31:49Z","parsedTime":"2020-07-07 04:31:49","unixTime":1594053109000,"elapsedTime":"00:50:04","incrementalDistance":14,"cumulativeDistance":2803,"wSpeed":23.400000000000002,"pSpeed":null,"isWave":true},{"originalTime":"2020-07-07T04:31:51Z","parsedTime":"2020-07-07 04:31:51","unixTime":1594053111000,"elapsedTime":"00:50:06","incrementalDistance":12,"cumulativeDistance":2815,"wSpeed":21.599999999999998,"pSpeed":null,"isWave":true},{"originalTime":"2020-07-07T04:31:53Z","parsedTime":"2020-07-07 04:31:53","unixTime":1594053113000,"elapsedTime":"00:50:08","incrementalDistance":16,"cumulativeDistance":2831,"wSpeed":19.2,"pSpeed":null,"isWave":true},{"originalTime":"2020-07-07T04:31:56Z","parsedTime":"2020-07-07 04:31:56","unixTime":1594053116000,"elapsedTime":"00:50:11","incrementalDistance":5,"cumulativeDistance":2836,"wSpeed":14.700000000000001,"pSpeed":null,"isWave":true},{"originalTime":"2020-07-07T04:31:57Z","parsedTime":"2020-07-07 04:31:57","unixTime":1594053117000,"elapsedTime":"00:50:12","incrementalDistance":18,"cumulativeDistance":2854,"wSpeed":9.9,"pSpeed":null,"isWave":true}],[{"originalTime":"2020-07-07T04:35:51Z","parsedTime":"2020-07-07 04:35:51","unixTime":1594053351000,"elapsedTime":"00:54:06","incrementalDistance":10,"cumulativeDistance":3130,"wSpeed":null,"pSpeed":7.6000000000000005,"isWave":false},{"originalTime":"2020-07-07T04:35:54Z","parsedTime":"2020-07-07 04:35:54","unixTime":1594053354000,"elapsedTime":"00:54:09","incrementalDistance":2,"cumulativeDistance":3132,"wSpeed":10,"pSpeed":null,"isWave":true},{"originalTime":"2020-07-07T04:35:55Z","parsedTime":"2020-07-07 04:35:55","unixTime":1594053355000,"elapsedTime":"00:54:10","incrementalDistance":3,"cumulativeDistance":3135,"wSpeed":8.4,"pSpeed":null,"isWave":true},{"originalTime":"2020-07-07T04:35:56Z","parsedTime":"2020-07-07 04:35:56","unixTime":1594053356000,"elapsedTime":"00:54:11","incrementalDistance":2,"cumulativeDistance":3137,"wSpeed":9.6,"pSpeed":null,"isWave":true},{"originalTime":"2020-07-07T04:35:57Z","parsedTime":"2020-07-07 04:35:57","unixTime":1594053357000,"elapsedTime":"00:54:12","incrementalDistance":3,"cumulativeDistance":3140,"wSpeed":8.4,"pSpeed":null,"isWave":true},{"originalTime":"2020-07-07T04:35:58Z","parsedTime":"2020-07-07 04:35:58","unixTime":1594053358000,"elapsedTime":"00:54:13","incrementalDistance":2,"cumulativeDistance":3142,"wSpeed":10.799999999999999,"pSpeed":null,"isWave":true},{"originalTime":"2020-07-07T04:35:59Z","parsedTime":"2020-07-07 04:35:59","unixTime":1594053359000,"elapsedTime":"00:54:14","incrementalDistance":4,"cumulativeDistance":3146,"wSpeed":8.266666666666667,"pSpeed":null,"isWave":true}],[{"originalTime":"2020-07-07T04:38:17Z","parsedTime":"2020-07-07 04:38:17","unixTime":1594053497000,"elapsedTime":"00:56:32","incrementalDistance":0,"cumulativeDistance":3260,"wSpeed":null,"pSpeed":0,"isWave":false},{"originalTime":"2020-07-07T04:38:21Z","parsedTime":"2020-07-07 04:38:21","unixTime":1594053501000,"elapsedTime":"00:56:36","incrementalDistance":0,"cumulativeDistance":3260,"wSpeed":10,"pSpeed":null,"isWave":true},{"originalTime":"2020-07-07T04:38:25Z","parsedTime":"2020-07-07 04:38:25","unixTime":1594053505000,"elapsedTime":"00:56:40","incrementalDistance":9,"cumulativeDistance":3269,"wSpeed":10,"pSpeed":null,"isWave":true},{"originalTime":"2020-07-07T04:38:26Z","parsedTime":"2020-07-07 04:38:26","unixTime":1594053506000,"elapsedTime":"00:56:41","incrementalDistance":0,"cumulativeDistance":3269,"wSpeed":10,"pSpeed":null,"isWave":true},{"originalTime":"2020-07-07T04:38:28Z","parsedTime":"2020-07-07 04:38:28","unixTime":1594053508000,"elapsedTime":"00:56:43","incrementalDistance":0,"cumulativeDistance":3269,"wSpeed":null,"pSpeed":0,"isWave":false},{"originalTime":"2020-07-07T04:38:29Z","parsedTime":"2020-07-07 04:38:29","unixTime":1594053509000,"elapsedTime":"00:56:44","incrementalDistance":0,"cumulativeDistance":3269,"wSpeed":10,"pSpeed":null,"isWave":true},{"originalTime":"2020-07-07T04:38:32Z","parsedTime":"2020-07-07 04:38:32","unixTime":1594053512000,"elapsedTime":"00:56:47","incrementalDistance":27,"cumulativeDistance":3296,"wSpeed":11.35,"pSpeed":null,"isWave":true},{"originalTime":"2020-07-07T04:38:35Z","parsedTime":"2020-07-07 04:38:35","unixTime":1594053515000,"elapsedTime":"00:56:50","incrementalDistance":9,"cumulativeDistance":3305,"wSpeed":11.35,"pSpeed":null,"isWave":true}],[{"originalTime":"2020-07-07T04:40:00Z","parsedTime":"2020-07-07 04:40:00","unixTime":1594053600000,"elapsedTime":"00:58:15","incrementalDistance":4,"cumulativeDistance":3405,"wSpeed":null,"pSpeed":7.800000000000001,"isWave":false},{"originalTime":"2020-07-07T04:40:02Z","parsedTime":"2020-07-07 04:40:02","unixTime":1594053602000,"elapsedTime":"00:58:17","incrementalDistance":3,"cumulativeDistance":3408,"wSpeed":8.4,"pSpeed":null,"isWave":true},{"originalTime":"2020-07-07T04:40:03Z","parsedTime":"2020-07-07 04:40:03","unixTime":1594053603000,"elapsedTime":"00:58:18","incrementalDistance":2,"cumulativeDistance":3410,"wSpeed":8.200000000000001,"pSpeed":null,"isWave":true},{"originalTime":"2020-07-07T04:40:04Z","parsedTime":"2020-07-07 04:40:04","unixTime":1594053604000,"elapsedTime":"00:58:19","incrementalDistance":11,"cumulativeDistance":3421,"wSpeed":11.4,"pSpeed":null,"isWave":true},{"originalTime":"2020-07-07T04:40:10Z","parsedTime":"2020-07-07 04:40:10","unixTime":1594053610000,"elapsedTime":"00:58:25","incrementalDistance":17,"cumulativeDistance":3438,"wSpeed":16.2,"pSpeed":null,"isWave":true},{"originalTime":"2020-07-07T04:40:13Z","parsedTime":"2020-07-07 04:40:13","unixTime":1594053613000,"elapsedTime":"00:58:28","incrementalDistance":18,"cumulativeDistance":3456,"wSpeed":22.400000000000002,"pSpeed":null,"isWave":true},{"originalTime":"2020-07-07T04:40:16Z","parsedTime":"2020-07-07 04:40:16","unixTime":1594053616000,"elapsedTime":"00:58:31","incrementalDistance":14,"cumulativeDistance":3470,"wSpeed":20.4,"pSpeed":null,"isWave":true},{"originalTime":"2020-07-07T04:40:18Z","parsedTime":"2020-07-07 04:40:18","unixTime":1594053618000,"elapsedTime":"00:58:33","incrementalDistance":12,"cumulativeDistance":3482,"wSpeed":16.2,"pSpeed":null,"isWave":true},{"originalTime":"2020-07-07T04:40:21Z","parsedTime":"2020-07-07 04:40:21","unixTime":1594053621000,"elapsedTime":"00:58:36","incrementalDistance":10,"cumulativeDistance":3492,"wSpeed":10.799999999999999,"pSpeed":null,"isWave":true}],[{"originalTime":"2020-07-07T04:53:23Z","parsedTime":"2020-07-07 04:53:23","unixTime":1594054403000,"elapsedTime":"01:11:38","incrementalDistance":7,"cumulativeDistance":4042,"wSpeed":null,"pSpeed":6.84,"isWave":false},{"originalTime":"2020-07-07T04:53:27Z","parsedTime":"2020-07-07 04:53:27","unixTime":1594054407000,"elapsedTime":"01:11:42","incrementalDistance":6,"cumulativeDistance":4048,"wSpeed":11.64,"pSpeed":null,"isWave":true},{"originalTime":"2020-07-07T04:53:32Z","parsedTime":"2020-07-07 04:53:32","unixTime":1594054412000,"elapsedTime":"01:11:47","incrementalDistance":27,"cumulativeDistance":4075,"wSpeed":11.340000000000002,"pSpeed":null,"isWave":true},{"originalTime":"2020-07-07T04:53:36Z","parsedTime":"2020-07-07 04:53:36","unixTime":1594054416000,"elapsedTime":"01:11:51","incrementalDistance":6,"cumulativeDistance":4081,"wSpeed":10.833333333333334,"pSpeed":null,"isWave":true}],[{"originalTime":"2020-07-07T05:01:18Z","parsedTime":"2020-07-07 05:01:18","unixTime":1594054878000,"elapsedTime":"01:19:33","incrementalDistance":0,"cumulativeDistance":4204,"wSpeed":null,"pSpeed":0,"isWave":false},{"originalTime":"2020-07-07T05:01:19Z","parsedTime":"2020-07-07 05:01:19","unixTime":1594054879000,"elapsedTime":"01:19:34","incrementalDistance":0,"cumulativeDistance":4204,"wSpeed":10,"pSpeed":null,"isWave":true},{"originalTime":"2020-07-07T05:01:20Z","parsedTime":"2020-07-07 05:01:20","unixTime":1594054880000,"elapsedTime":"01:19:35","incrementalDistance":54,"cumulativeDistance":4258,"wSpeed":10.685714285714285,"pSpeed":null,"isWave":true},{"originalTime":"2020-07-07T05:01:23Z","parsedTime":"2020-07-07 05:01:23","unixTime":1594054883000,"elapsedTime":"01:19:38","incrementalDistance":4,"cumulativeDistance":4262,"wSpeed":17.885714285714286,"pSpeed":null,"isWave":true},{"originalTime":"2020-07-07T05:01:30Z","parsedTime":"2020-07-07 05:01:30","unixTime":1594054890000,"elapsedTime":"01:19:45","incrementalDistance":6,"cumulativeDistance":4268,"wSpeed":9.085714285714287,"pSpeed":null,"isWave":true},{"originalTime":"2020-07-07T05:01:31Z","parsedTime":"2020-07-07 05:01:31","unixTime":1594054891000,"elapsedTime":"01:19:46","incrementalDistance":2,"cumulativeDistance":4270,"wSpeed":9.600000000000001,"pSpeed":null,"isWave":true}],[{"originalTime":"2020-07-07T05:01:44Z","parsedTime":"2020-07-07 05:01:44","unixTime":1594054904000,"elapsedTime":"01:19:59","incrementalDistance":8,"cumulativeDistance":4294,"wSpeed":null,"pSpeed":5.2384615384615385,"isWave":false},{"originalTime":"2020-07-07T05:01:57Z","parsedTime":"2020-07-07 05:01:57","unixTime":1594054917000,"elapsedTime":"01:20:12","incrementalDistance":7,"cumulativeDistance":4301,"wSpeed":12.438461538461539,"pSpeed":null,"isWave":true},{"originalTime":"2020-07-07T05:02:01Z","parsedTime":"2020-07-07 05:02:01","unixTime":1594054921000,"elapsedTime":"01:20:16","incrementalDistance":8,"cumulativeDistance":4309,"wSpeed":16.5,"pSpeed":null,"isWave":true},{"originalTime":"2020-07-07T05:02:02Z","parsedTime":"2020-07-07 05:02:02","unixTime":1594054922000,"elapsedTime":"01:20:17","incrementalDistance":4,"cumulativeDistance":4313,"wSpeed":20.400000000000002,"pSpeed":null,"isWave":true},{"originalTime":"2020-07-07T05:02:03Z","parsedTime":"2020-07-07 05:02:03","unixTime":1594054923000,"elapsedTime":"01:20:18","incrementalDistance":5,"cumulativeDistance":4318,"wSpeed":14.4,"pSpeed":null,"isWave":true},{"originalTime":"2020-07-07T05:02:04Z","parsedTime":"2020-07-07 05:02:04","unixTime":1594054924000,"elapsedTime":"01:20:19","incrementalDistance":6,"cumulativeDistance":4324,"wSpeed":13.200000000000001,"pSpeed":null,"isWave":true},{"originalTime":"2020-07-07T05:02:06Z","parsedTime":"2020-07-07 05:02:06","unixTime":1594054926000,"elapsedTime":"01:20:21","incrementalDistance":3,"cumulativeDistance":4327,"wSpeed":13.200000000000001,"pSpeed":null,"isWave":true},{"originalTime":"2020-07-07T05:02:07Z","parsedTime":"2020-07-07 05:02:07","unixTime":1594054927000,"elapsedTime":"01:20:22","incrementalDistance":5,"cumulativeDistance":4332,"wSpeed":14.4,"pSpeed":null,"isWave":true},{"originalTime":"2020-07-07T05:02:08Z","parsedTime":"2020-07-07 05:02:08","unixTime":1594054928000,"elapsedTime":"01:20:23","incrementalDistance":16,"cumulativeDistance":4348,"wSpeed":14.057142857142857,"pSpeed":null,"isWave":true},{"originalTime":"2020-07-07T05:02:12Z","parsedTime":"2020-07-07 05:02:12","unixTime":1594054932000,"elapsedTime":"01:20:27","incrementalDistance":19,"cumulativeDistance":4367,"wSpeed":9.577142857142857,"pSpeed":null,"isWave":true}],[{"originalTime":"2020-07-07T05:10:56Z","parsedTime":"2020-07-07 05:10:56","unixTime":1594055456000,"elapsedTime":"01:29:11","incrementalDistance":0,"cumulativeDistance":4631,"wSpeed":null,"pSpeed":0,"isWave":false},{"originalTime":"2020-07-07T05:10:58Z","parsedTime":"2020-07-07 05:10:58","unixTime":1594055458000,"elapsedTime":"01:29:13","incrementalDistance":0,"cumulativeDistance":4631,"wSpeed":10,"pSpeed":null,"isWave":true},{"originalTime":"2020-07-07T05:11:10Z","parsedTime":"2020-07-07 05:11:10","unixTime":1594055470000,"elapsedTime":"01:29:25","incrementalDistance":49,"cumulativeDistance":4680,"wSpeed":11.92,"pSpeed":null,"isWave":true},{"originalTime":"2020-07-07T05:11:14Z","parsedTime":"2020-07-07 05:11:14","unixTime":1594055474000,"elapsedTime":"01:29:29","incrementalDistance":8,"cumulativeDistance":4688,"wSpeed":13.12,"pSpeed":null,"isWave":true}],[{"originalTime":"2020-07-07T05:11:32Z","parsedTime":"2020-07-07 05:11:32","unixTime":1594055492000,"elapsedTime":"01:29:47","incrementalDistance":1,"cumulativeDistance":4702,"wSpeed":null,"pSpeed":4.8,"isWave":false},{"originalTime":"2020-07-07T05:11:33Z","parsedTime":"2020-07-07 05:11:33","unixTime":1594055493000,"elapsedTime":"01:29:48","incrementalDistance":2,"cumulativeDistance":4704,"wSpeed":9.6,"pSpeed":null,"isWave":true},{"originalTime":"2020-07-07T05:11:34Z","parsedTime":"2020-07-07 05:11:34","unixTime":1594055494000,"elapsedTime":"01:29:49","incrementalDistance":5,"cumulativeDistance":4709,"wSpeed":9.6,"pSpeed":null,"isWave":true},{"originalTime":"2020-07-07T05:11:35Z","parsedTime":"2020-07-07 05:11:35","unixTime":1594055495000,"elapsedTime":"01:29:50","incrementalDistance":1,"cumulativeDistance":4710,"wSpeed":8.4,"pSpeed":null,"isWave":true}],[{"originalTime":"2020-07-07T05:14:32Z","parsedTime":"2020-07-07 05:14:32","unixTime":1594055672000,"elapsedTime":"01:32:47","incrementalDistance":0,"cumulativeDistance":4757,"wSpeed":null,"pSpeed":1.2,"isWave":false},{"originalTime":"2020-07-07T05:14:56Z","parsedTime":"2020-07-07 05:14:56","unixTime":1594055696000,"elapsedTime":"01:33:11","incrementalDistance":0,"cumulativeDistance":4757,"wSpeed":10,"pSpeed":null,"isWave":true},{"originalTime":"2020-07-07T05:14:57Z","parsedTime":"2020-07-07 05:14:57","unixTime":1594055697000,"elapsedTime":"01:33:12","incrementalDistance":17,"cumulativeDistance":4774,"wSpeed":10.975,"pSpeed":null,"isWave":true},{"originalTime":"2020-07-07T05:14:59Z","parsedTime":"2020-07-07 05:14:59","unixTime":1594055699000,"elapsedTime":"01:33:14","incrementalDistance":13,"cumulativeDistance":4787,"wSpeed":10.975,"pSpeed":null,"isWave":true},{"originalTime":"2020-07-07T05:15:15Z","parsedTime":"2020-07-07 05:15:15","unixTime":1594055715000,"elapsedTime":"01:33:30","incrementalDistance":0,"cumulativeDistance":4787,"wSpeed":10.975,"pSpeed":null,"isWave":true},{"originalTime":"2020-07-07T05:15:28Z","parsedTime":"2020-07-07 05:15:28","unixTime":1594055728000,"elapsedTime":"01:33:43","incrementalDistance":51,"cumulativeDistance":4838,"wSpeed":10,"pSpeed":null,"isWave":true},{"originalTime":"2020-07-07T05:15:34Z","parsedTime":"2020-07-07 05:15:34","unixTime":1594055734000,"elapsedTime":"01:33:49","incrementalDistance":0,"cumulativeDistance":4838,"wSpeed":10,"pSpeed":null,"isWave":true}],[{"originalTime":"2020-07-07T05:18:51Z","parsedTime":"2020-07-07 05:18:51","unixTime":1594055931000,"elapsedTime":"01:37:06","incrementalDistance":6,"cumulativeDistance":4928,"wSpeed":null,"pSpeed":2.222608695652174,"isWave":false},{"originalTime":"2020-07-07T05:18:56Z","parsedTime":"2020-07-07 05:18:56","unixTime":1594055936000,"elapsedTime":"01:37:11","incrementalDistance":0,"cumulativeDistance":4928,"wSpeed":8.94,"pSpeed":null,"isWave":true},{"originalTime":"2020-07-07T05:19:16Z","parsedTime":"2020-07-07 05:19:16","unixTime":1594055956000,"elapsedTime":"01:37:31","incrementalDistance":25,"cumulativeDistance":4953,"wSpeed":9.15,"pSpeed":null,"isWave":true},{"originalTime":"2020-07-07T05:19:20Z","parsedTime":"2020-07-07 05:19:20","unixTime":1594055960000,"elapsedTime":"01:37:35","incrementalDistance":22,"cumulativeDistance":4975,"wSpeed":11.549999999999999,"pSpeed":null,"isWave":true}],[{"originalTime":"2020-07-07T05:23:30Z","parsedTime":"2020-07-07 05:23:30","unixTime":1594056210000,"elapsedTime":"01:41:45","incrementalDistance":1,"cumulativeDistance":5139,"wSpeed":null,"pSpeed":7.2,"isWave":false},{"originalTime":"2020-07-07T05:23:31Z","parsedTime":"2020-07-07 05:23:31","unixTime":1594056211000,"elapsedTime":"01:41:46","incrementalDistance":3,"cumulativeDistance":5142,"wSpeed":9.6,"pSpeed":null,"isWave":true},{"originalTime":"2020-07-07T05:23:32Z","parsedTime":"2020-07-07 05:23:32","unixTime":1594056212000,"elapsedTime":"01:41:47","incrementalDistance":4,"cumulativeDistance":5146,"wSpeed":15.600000000000001,"pSpeed":null,"isWave":true},{"originalTime":"2020-07-07T05:23:33Z","parsedTime":"2020-07-07 05:23:33","unixTime":1594056213000,"elapsedTime":"01:41:48","incrementalDistance":6,"cumulativeDistance":5152,"wSpeed":18,"pSpeed":null,"isWave":true},{"originalTime":"2020-07-07T05:23:34Z","parsedTime":"2020-07-07 05:23:34","unixTime":1594056214000,"elapsedTime":"01:41:49","incrementalDistance":5,"cumulativeDistance":5157,"wSpeed":16.400000000000002,"pSpeed":null,"isWave":true},{"originalTime":"2020-07-07T05:23:35Z","parsedTime":"2020-07-07 05:23:35","unixTime":1594056215000,"elapsedTime":"01:41:50","incrementalDistance":8,"cumulativeDistance":5165,"wSpeed":11.600000000000001,"pSpeed":null,"isWave":true},{"originalTime":"2020-07-07T05:23:38Z","parsedTime":"2020-07-07 05:23:38","unixTime":1594056218000,"elapsedTime":"01:41:53","incrementalDistance":2,"cumulativeDistance":5167,"wSpeed":8,"pSpeed":null,"isWave":true}],[{"originalTime":"2020-07-07T05:24:07Z","parsedTime":"2020-07-07 05:24:07","unixTime":1594056247000,"elapsedTime":"01:42:22","incrementalDistance":12,"cumulativeDistance":5206,"wSpeed":null,"pSpeed":5.04,"isWave":false},{"originalTime":"2020-07-07T05:24:17Z","parsedTime":"2020-07-07 05:24:17","unixTime":1594056257000,"elapsedTime":"01:42:32","incrementalDistance":6,"cumulativeDistance":5212,"wSpeed":13.44,"pSpeed":null,"isWave":true},{"originalTime":"2020-07-07T05:24:20Z","parsedTime":"2020-07-07 05:24:20","unixTime":1594056260000,"elapsedTime":"01:42:35","incrementalDistance":8,"cumulativeDistance":5220,"wSpeed":13.200000000000001,"pSpeed":null,"isWave":true},{"originalTime":"2020-07-07T05:24:21Z","parsedTime":"2020-07-07 05:24:21","unixTime":1594056261000,"elapsedTime":"01:42:36","incrementalDistance":1,"cumulativeDistance":5221,"wSpeed":11.399999999999999,"pSpeed":null,"isWave":true}],[{"originalTime":"2020-07-07T05:25:41Z","parsedTime":"2020-07-07 05:25:41","unixTime":1594056341000,"elapsedTime":"01:43:56","incrementalDistance":0,"cumulativeDistance":5249,"wSpeed":null,"pSpeed":0,"isWave":false},{"originalTime":"2020-07-07T05:25:43Z","parsedTime":"2020-07-07 05:25:43","unixTime":1594056343000,"elapsedTime":"01:43:58","incrementalDistance":0,"cumulativeDistance":5249,"wSpeed":9.6,"pSpeed":null,"isWave":true},{"originalTime":"2020-07-07T05:25:46Z","parsedTime":"2020-07-07 05:25:46","unixTime":1594056346000,"elapsedTime":"01:44:01","incrementalDistance":16,"cumulativeDistance":5265,"wSpeed":9.657142857142857,"pSpeed":null,"isWave":true},{"originalTime":"2020-07-07T05:25:48Z","parsedTime":"2020-07-07 05:25:48","unixTime":1594056348000,"elapsedTime":"01:44:03","incrementalDistance":1,"cumulativeDistance":5266,"wSpeed":10.857142857142856,"pSpeed":null,"isWave":true}],[{"originalTime":"2020-07-07T05:29:26Z","parsedTime":"2020-07-07 05:29:26","unixTime":1594056566000,"elapsedTime":"01:47:41","incrementalDistance":1,"cumulativeDistance":5322,"wSpeed":null,"pSpeed":2.8000000000000003,"isWave":false},{"originalTime":"2020-07-07T05:29:29Z","parsedTime":"2020-07-07 05:29:29","unixTime":1594056569000,"elapsedTime":"01:47:44","incrementalDistance":1,"cumulativeDistance":5323,"wSpeed":11.6,"pSpeed":null,"isWave":true},{"originalTime":"2020-07-07T05:29:30Z","parsedTime":"2020-07-07 05:29:30","unixTime":1594056570000,"elapsedTime":"01:47:45","incrementalDistance":47,"cumulativeDistance":5370,"wSpeed":19,"pSpeed":null,"isWave":true},{"originalTime":"2020-07-07T05:29:31Z","parsedTime":"2020-07-07 05:29:31","unixTime":1594056571000,"elapsedTime":"01:47:46","incrementalDistance":13,"cumulativeDistance":5383,"wSpeed":24.040000000000003,"pSpeed":null,"isWave":true},{"originalTime":"2020-07-07T05:29:33Z","parsedTime":"2020-07-07 05:29:33","unixTime":1594056573000,"elapsedTime":"01:47:48","incrementalDistance":52,"cumulativeDistance":5435,"wSpeed":18.040000000000003,"pSpeed":null,"isWave":true},{"originalTime":"2020-07-07T05:29:43Z","parsedTime":"2020-07-07 05:29:43","unixTime":1594056583000,"elapsedTime":"01:47:58","incrementalDistance":11,"cumulativeDistance":5446,"wSpeed":11.32,"pSpeed":null,"isWave":true}]]